nuclino/__init__.py
nuclino/api.py
nuclino/objects.py
nuclino/utils.py
PyNuclino-0.2.1.dist-info/LICENSE
PyNuclino-0.2.1.dist-info/METADATA
PyNuclino-0.2.1.dist-info/WHEEL
PyNuclino-0.2.1.dist-info/top_level.txt
PyNuclino-0.2.1.dist-info/RECORD
