Metadata-Version: 2.1
Name: PyNuclino
Version: 0.2.1
Summary: Nuclino API wrapper
Home-page: https://github.com/Vanderhoof/PyNuclino
Author: Daniel Minukhin
Author-email: ddddsa@gmail.com
License: MIT
Platform: any
Classifier: Development Status :: 4 - Beta
Classifier: Environment :: Console
Classifier: Intended Audience :: Developers
Classifier: License :: OSI Approved :: MIT License
Classifier: Operating System :: OS Independent
Classifier: Programming Language :: Python
Classifier: Topic :: Documentation
Classifier: Topic :: Text Processing :: Markup
Classifier: Topic :: Utilities
Requires-Python: >=3.7
License-File: LICENSE
Requires-Dist: ratelimit
Requires-Dist: requests
